resolver/__init__.py
resolver/daytona_patch.py
resolver/error_tracker.py
resolver/listen_for_decision.py
resolver/prompts/resolve/basic-conversation-instructions.jinja
resolver/prompts/resolve/basic-followup-conversation-instructions.jinja
resolver/prompts/resolve/basic-followup.jinja
resolver/prompts/resolve/basic-with-tests-conversation-instructions.jinja
resolver/prompts/resolve/basic-with-tests.jinja
resolver/prompts/resolve/basic.jinja
resolver/prompts/resolve/pr-changes-summary.jinja
resolver/resolve_issue.py
resolver/resolver_output.py
resolver/secrets.py
resolver/send_pull_request.py
resolver/utils.py
pr_arena-0.2.9.dist-info/METADATA
pr_arena-0.2.9.dist-info/WHEEL
pr_arena-0.2.9.dist-info/licenses/LICENSE
pr_arena-0.2.9.dist-info/RECORD
