Metadata-Version: 2.4
Name: pr-arena
Version: 0.2.9
Summary: PR-Arena: Arena Setting for GitHub Issue Resolver
License: MIT
License-File: LICENSE
Author: OpenHands
Requires-Python: >=3.12,<3.14
Classifier: Development Status :: 4 - Beta
Classifier: Intended Audience :: Developers
Classifier: License :: OSI Approved :: MIT License
Classifier: Programming Language :: Python :: 3
Classifier: Programming Language :: Python :: 3.12
Classifier: Programming Language :: Python :: 3.13
Classifier: Topic :: Software Development :: Bug Tracking
Classifier: Topic :: Software Development :: Libraries :: Python Modules
Classifier: Topic :: Software Development :: Version Control :: Git
Requires-Dist: firebase-admin (>=6.6.0,<7.0.0)
Requires-Dist: openai (>=1.99.5,<1.109.0)
Requires-Dist: openhands-ai (==0.40.0)
Project-URL: Homepage, https://github.com/neulab/pr-arena
Project-URL: Repository, https://github.com/neulab/pr-arena
